meilisearchdsl/__init__.py
meilisearchdsl/client.py
meilisearchdsl/index.py
meilisearchdsl/index_query.py
meilisearchdsl/query.py
meilisearchdsl/test.py
meilisearchdsl-0.1.7.dist-info/LICENSE
meilisearchdsl-0.1.7.dist-info/METADATA
meilisearchdsl-0.1.7.dist-info/WHEEL
meilisearchdsl-0.1.7.dist-info/top_level.txt
meilisearchdsl-0.1.7.dist-info/RECORD
