Metadata-Version: 2.1
Name: meilisearchdsl
Version: 0.1.7
Summary: MeiliSearch DSL is a Python package providing a Django-like Q object syntax for querying MeiliSearch, an open-source search engine. It simplifies search query building and offers a convenient wrapper for MeiliSearch indexes and clients, streamlining search interactions and improving maintainability.
Home-page: https://github.com/UnattendedFlight/meilisearch-dsl
Author: Adrian Leo
Classifier: Development Status :: 3 - Alpha
Classifier: Intended Audience :: Developers
Classifier: License :: OSI Approved :: MIT License
Classifier: Programming Language :: Python
Classifier: Programming Language :: Python :: 3
Classifier: Programming Language :: Python :: 3.6
Classifier: Programming Language :: Python :: 3.7
Classifier: Programming Language :: Python :: 3.8
License-File: LICENSE
Requires-Dist: meilisearch (==0.26.0)
